best/__init__.py
best/integration/__init__.py
best/unit/__init__.py
best/unit/conftest.py
best/unit/test_glue_session.py
best/unit/test_glue_session_demo.py
best/unit/test_session_apis.py
torch_ort_inference-100.0.5.dist-info/LICENSE.txt
torch_ort_inference-100.0.5.dist-info/METADATA
torch_ort_inference-100.0.5.dist-info/WHEEL
torch_ort_inference-100.0.5.dist-info/top_level.txt
torch_ort_inference-100.0.5.dist-info/RECORD
