Metadata-Version: 2.1
Name: torch-ort-inference
Version: 100.0.5
Summary: torch-ort-inference of torch-ort-inference of torch-ort-inference
Home-page: UNKNOWN
Author: Alon walker
Author-email: alonwalker@facebook.com
License: UNKNOWN
Platform: UNKNOWN
Classifier: Programming Language :: Python :: 3
Classifier: License :: OSI Approved :: MIT License
Classifier: Operating System :: OS Independent
